pgvacuum/__init__.py
pgvacuum/__main__.py
pgvacuum/pg_vacuum.py
pg_vacuum-0.1a10.dist-info/LICENSE
pg_vacuum-0.1a10.dist-info/METADATA
pg_vacuum-0.1a10.dist-info/WHEEL
pg_vacuum-0.1a10.dist-info/entry_points.txt
pg_vacuum-0.1a10.dist-info/top_level.txt
pg_vacuum-0.1a10.dist-info/RECORD
